frange/__init__.py
frange/frange.py
frange_py-1.0.0.dist-info/LICENSE
frange_py-1.0.0.dist-info/METADATA
frange_py-1.0.0.dist-info/WHEEL
frange_py-1.0.0.dist-info/top_level.txt
frange_py-1.0.0.dist-info/RECORD
